td_ml_auto_build_segments/__init__.py
td_ml_auto_build_segments/autobuild_segments.py
td_ml_auto_build_segments-0.1.2.dist-info/METADATA
td_ml_auto_build_segments-0.1.2.dist-info/WHEEL
td_ml_auto_build_segments-0.1.2.dist-info/licenses/LICENSE
td_ml_auto_build_segments-0.1.2.dist-info/RECORD
