Metadata-Version: 2.1
Name: td_ml_auto_build_segments
Version: 0.1.2
Summary: TD Auto Build Segments in Audience Studio
Project-URL: Homepage, https://github.com/treasure-data-ps/td_ml_auto_build_segments
Project-URL: Bug Tracker, https://github.com/treasure-data-ps/td_ml_auto_build_segments
Author-email: Dilyan Kovachev <pruchka@gmail.com>
License: Copyright © 2022 Treasure Data, Inc. (or its affiliates). All rights reserved
License-File: LICENSE
Classifier: Operating System :: OS Independent
Classifier: Programming Language :: Python :: 3
Requires-Python: >=3.8
